cfwafenabler/__init__.py
cfwafenabler/__main__.py
cfwafenabler-0.0.2.dist-info/entry_points.txt
cfwafenabler-0.0.2.dist-info/WHEEL
cfwafenabler-0.0.2.dist-info/METADATA
cfwafenabler-0.0.2.dist-info/RECORD
