Metadata-Version: 2.1
Name: cfwafenabler
Version: 0.0.2
Summary: Allows to mass modify rules in CloudFlare WAF
Home-page: https://github.com/nomex/cfwafenabler
Author: David Lladro
Author-email: david.lladro@gmail.com
Requires-Python: >=3.8.0,<4.0.0
Classifier: Environment :: Console
Classifier: Programming Language :: Python :: 3
Classifier: Programming Language :: Python :: 3.8
Classifier: Programming Language :: Python :: 3.9
Classifier: Topic :: Security
Requires-Dist: cloudflare (>=2.8.15,<3.0.0)
Requires-Dist: configparser (>=5.0.1,<6.0.0)
Requires-Dist: requests (>=2.25.1,<3.0.0)
Requires-Dist: simple-term-menu (>=0.10.5,<0.11.0)
Project-URL: Repository, https://github.com/nomex/cfwafenabler
